halite_agent/__init__.py
halite_agent/api/KaggleClient.py
halite_agent/api/__init__.py
halite_agent/data/__init__.py
halite_agent/data/fetch_dataset.py
halite_agent/data/make_dataset.py
halite_agent/features/__init__.py
halite_agent/features/build_features.py
halite_agent/visualization/__init__.py
halite_agent/visualization/visualize.py
halite_agent-0.1.1.dist-info/LICENSE
halite_agent-0.1.1.dist-info/METADATA
halite_agent-0.1.1.dist-info/WHEEL
halite_agent-0.1.1.dist-info/top_level.txt
halite_agent-0.1.1.dist-info/RECORD
