Metadata-Version: 2.1
Name: halite-agent
Version: 0.1.1
Summary: The challenge is to create an agent that can succeed in the game of Halite IV.  (Kaggle Proj) https://www.kaggle.com/c/halite
Home-page: https://github.com/iainwo/kaggle/tree/master/halite
Author: Iain Wong
Author-email: iainwong@outlook.com
License: MIT
Platform: UNKNOWN
Classifier: Programming Language :: Python :: 3
Classifier: License :: OSI Approved :: MIT License
Classifier: Operating System :: OS Independent
Requires-Python: >=3.6
Requires-Dist: pandas
Requires-Dist: python-dotenv
Requires-Dist: Click
